newslookout/__init__.py
newslookout/base_plugin.py
newslookout/config.py
newslookout/data_structs.py
newslookout/network.py
newslookout/news_event.py
newslookout/queue_manager.py
newslookout/scraper_app.py
newslookout/scraper_utils.py
newslookout/session_hist.py
newslookout/worker.py
newslookout/plugins/__init__.py
newslookout/plugins/mod_dataprep.py
newslookout/plugins/mod_dedupe.py
newslookout/plugins/mod_en_in_business_std.py
newslookout/plugins/mod_en_in_ecotimes.py
newslookout/plugins/mod_en_in_forbes.py
newslookout/plugins/mod_en_in_hindu.py
newslookout/plugins/mod_en_in_indiakanoon.py
newslookout/plugins/mod_en_in_inexp_business.py
newslookout/plugins/mod_en_in_livemint.py
newslookout/plugins/mod_en_in_moneycontrol.py
newslookout/plugins/mod_en_in_ndtv.py
newslookout/plugins/mod_en_in_timesofindia.py
newslookout/plugins/mod_en_in_trak.py
newslookout/plugins/mod_eventclass.py
newslookout/plugins/mod_in_bse.py
newslookout/plugins/mod_in_gdelt.py
newslookout/plugins/mod_in_nse.py
newslookout/plugins/mod_json_to_csv.py
newslookout/plugins/mod_keywordflags.py
newslookout/plugins/mod_solrsubmit.py
newslookout/plugins_contrib/template_for_plugin.py
NewsLookout-2.1.0.dist-info/LICENSE
NewsLookout-2.1.0.dist-info/METADATA
NewsLookout-2.1.0.dist-info/WHEEL
NewsLookout-2.1.0.dist-info/entry_points.txt
NewsLookout-2.1.0.dist-info/top_level.txt
NewsLookout-2.1.0.dist-info/RECORD
