Metadata-Version: 2.1
Name: NewsLookout
Version: 2.1.0
Summary: News scraping application
Home-page: https://github.com/sandeep-sandhu/NewsLookout
Author: Sandeep Singh Sandhu
Author-email: sandeep.sandhu@gmx.com
Maintainer: Sandeep Singh Sandhu
License: GPL-3
Keywords: Web-scraping,News,NLP,Information-Retrieval,crawler
Platform: Operating System :: MacOS :: MacOS X
Platform: Operating System :: Microsoft :: Windows
Platform: Operating System :: POSIX
Classifier: Development Status :: 5 - Production/Stable
Classifier: Environment :: Console
Classifier: Environment :: No Input/Output (Daemon)
Classifier: Intended Audience :: Financial and Insurance Industry
Classifier: Operating System :: OS Independent
Classifier: Programming Language :: Python :: 3.7
Classifier: Programming Language :: Python :: 3.8
Classifier: Programming Language :: Python :: 3.9
Classifier: Programming Language :: Python :: 3.10
Classifier: Topic :: Internet :: WWW/HTTP :: Indexing/Search
License-File: LICENSE
Requires-Dist: newspaper3k
Requires-Dist: beautifulsoup4
Requires-Dist: lxml
Requires-Dist: nltk
Requires-Dist: spacy
Requires-Dist: requests
Requires-Dist: enlighten
Requires-Dist: pandas
Requires-Dist: numpy
Requires-Dist: tld
Requires-Dist: urllib3
Requires-Dist: configparser
Requires-Dist: openpyxl
